<?xml version="1.0"?>
<content collectionGUID="F27D61BF-0911-4E7F-94E4-A327692575EA">
  <lastEdited clientType="local-build-20180610" date="2018-06-10 15:37:21 +0000"/>
  <textBox id="generic-header-attribute" dynamic="no" visible="yes">
    <richText>New journal article</richText>
  </textBox>
  <textBox id="generic-body-attributes" dynamic="no" visible="yes">
    <richText>A new journal article resulting from a joint work between the team and the University Autonoma de Madrid (UAM) on face, iris and fingerprint anti-spoofing has been accepted for publication to Transactions on Image Processing:&#xD;&#xD;J.&#xA0;Galbally, S.&#xA0;Marcel, and J.&#xA0;Fierrez. Image quality assessment for fake biometric detection: Application to iris, fingerprint and face recognition. &#x2028;IEEE Transactions on Image Processing, 2013. [&lt;a href="http://ieeexplore.ieee.org/xpl/articleDetails.jsp?arnumber=6671991"&gt;IEEEXplore&lt;/a&gt;]&#x2028;</richText>
  </textBox>
  <textBox id="generic-datefield-attributes" dynamic="no" visible="yes">
    <richText>Monday 16 December 2013</richText>
  </textBox>
  <textBox id="generic-title-attributes" dynamic="no" visible="yes">
    <richText>New journal article in Transactions on Image Processing</richText>
  </textBox>
  <image id="generic-picture-attributes" dynamic="no" visible="yes" src="16_New_journal_article_in_Transactions_on_Image_Processing_files/shapeimage_2.png" left="0px" top="0px" width="356px" height="275px"/>
</content>
